{
  "run_timestamp": null,
  "data_path": "Output\\Preprocessing\\1781913101138\\full_preprocessed.csv",
  "target_column": "Sex",
  "problem_type": "classification",
  "model_selection": {
    "use_automl": true,
    "automl_config": {
      "models": [
        "GBM",
        "XGB"
      ],
      "time_limit": 300,
      "preset": "best_quality"
    },
    "selected_models": [],
    "model_selection_reasoning": "```json\n{\n  \"approach\": \"AutoGluon\",\n  \"reasoning\": \"The signal analysis reveals several strong to very strong univariate signals (e.g., '2urvived' at 254.96, 'Parch' at 62.19, 'Fare' at 46.67, 'Pclass' at 20.61). These strong signals indicate that the target 'Sex' is highly predictable from the features. AutoGluon is well-suited for datasets with strong, potentially complex or non-linear signals, as it automatically explores a wide range of models, including tree-based methods like Gradient Boosting Machines (GBM) and XGBoost, and ensembles them to achieve high performance. Given the absence of information suggesting a 'very large dataset' (which would favor Dask-XGBoost) or purely linear signals (which might favor 'Simple Training' with linear models), AutoGluon provides the most robust and automated approach to leverage these strong signals effectively.\",\n  \"autogluon_settings\": {\n    \"models_to_prioritize\": [\"GBM\", \"XGB\"],\n    \"time_limit_seconds\": 300,\n    \"preset_mode\": \"best_quality\"\n  },\n  \"simple_models\": [\"RandomForest\", \"XGBoost\", \"LogisticRegression\"],\n  \"dask_models\": [\"Dask-XGBoost\"]\n}\n```"
  },
  "training_results": {
    "best_model": "XGBoost_BAG_L1",
    "best_score": 0.7745940783190067,
    "feature_importance": {
      "2urvived": 0.15243553008595995,
      "Fare": 0.11365807067812801,
      "Age": 0.09169054441260746,
      "Parch": 0.06093600764087872,
      "Embarked": 0.02139446036294177,
      "sibsp": 0.00916905444126077,
      "Pclass": 0.005730659025788021
    },
    "models_trained": 3,
    "all_models": [
      "XGBoost_BAG_L1",
      "WeightedEnsemble_L2",
      "LightGBM_BAG_L1"
    ],
    "all_scores": [
      0.7745940783190067,
      0.7745940783190067,
      0.7688634192932188
    ],
    "training_method": "AutoGluon",
    "f1_score": 0.7500383494109998,
    "confusion_matrix": [
      [
        144,
        30
      ],
      [
        35,
        53
      ]
    ]
  },
  "agent_messages": [
    {
      "agent": "training",
      "message": "Training complete. 1.  **Performance Assessment:** The model shows good initial performance with a score of 0.7746 (likely accuracy or a similar metric) and an accuracy of approximately 75% based on the confusion matrix.\n2.  **False Positives vs. False Negatives:** There are slightly more False Negatives (35) than False Positives (30).\n3.  **Recommendations for Improvement:** Since AutoGluon only trained 3 models, allow it to run for a longer duration or with higher quality presets (e.g., `'best_quality'`) to explore more diverse models and deeper ensembles. Additionally, consider feature engineering or addressing potential class imbalance, given the difference in TN (144) and TP (53)."
    }
  ],
  "workflow": {
    "final_step": "model_trained",
    "error": null
  }
}